rdfmap/__init__.py
rdfmap/__main__.py
rdfmap/analyzer/__init__.py
rdfmap/analyzer/alignment_stats.py
rdfmap/cli/__init__.py
rdfmap/cli/interactive_review.py
rdfmap/cli/main.py
rdfmap/cli/wizard.py
rdfmap/config/__init__.py
rdfmap/config/loader.py
rdfmap/config/yarrrml_generator.py
rdfmap/config/yarrrml_parser.py
rdfmap/emitter/__init__.py
rdfmap/emitter/columnwise_builder.py
rdfmap/emitter/graph_builder.py
rdfmap/emitter/nt_streaming.py
rdfmap/emitter/streaming_graph_builder.py
rdfmap/generator/__init__.py
rdfmap/generator/confidence_calibrator.py
rdfmap/generator/data_analyzer.py
rdfmap/generator/embedding_cache.py
rdfmap/generator/evidence_categorizer.py
rdfmap/generator/graph_reasoner.py
rdfmap/generator/mapping_generator.py
rdfmap/generator/mapping_history.py
rdfmap/generator/matching_logger.py
rdfmap/generator/multisheet_analyzer.py
rdfmap/generator/ontology_analyzer.py
rdfmap/generator/ontology_enricher.py
rdfmap/generator/polars_helpers.py
rdfmap/generator/semantic_matcher.py
rdfmap/generator/spreadsheet_analyzer.py
rdfmap/generator/yaml_formatter.py
rdfmap/generator/matchers/__init__.py
rdfmap/generator/matchers/base.py
rdfmap/generator/matchers/datatype_matcher.py
rdfmap/generator/matchers/exact_matchers.py
rdfmap/generator/matchers/factory.py
rdfmap/generator/matchers/fuzzy_matchers.py
rdfmap/generator/matchers/graph_matcher.py
rdfmap/generator/matchers/hierarchy_matcher.py
rdfmap/generator/matchers/history_matcher.py
rdfmap/generator/matchers/lexical_matcher.py
rdfmap/generator/matchers/owl_characteristics_matcher.py
rdfmap/generator/matchers/restriction_matcher.py
rdfmap/generator/matchers/semantic_matcher.py
rdfmap/generator/matchers/skos_relations_matcher.py
rdfmap/generator/matchers/structural_matcher.py
rdfmap/iri/__init__.py
rdfmap/iri/generator.py
rdfmap/models/__init__.py
rdfmap/models/alignment.py
rdfmap/models/enrichment.py
rdfmap/models/errors.py
rdfmap/models/mapping.py
rdfmap/parsers/__init__.py
rdfmap/parsers/data_source.py
semantic_rdf_mapper-0.3.0.dist-info/licenses/LICENSE
semantic_rdf_mapper-0.3.0.dist-info/METADATA
semantic_rdf_mapper-0.3.0.dist-info/WHEEL
semantic_rdf_mapper-0.3.0.dist-info/entry_points.txt
semantic_rdf_mapper-0.3.0.dist-info/top_level.txt
semantic_rdf_mapper-0.3.0.dist-info/RECORD
