Metadata-Version: 2.4
Name: semantic-rdf-mapper
Version: 0.3.0
Summary: Convert tabular data (CSV, Excel, JSON, XML) to RDF triples aligned with OWL ontologies using SKOS-based semantic mapping
Author: Enterprise Data Engineering
Author-email: RDFMap Contributors <rxcthefirst@gmail.com>
Maintainer-email: RDFMap Team <rxcthefirst@gmail.com>
License-Expression: MIT
Project-URL: Homepage, https://github.com/rxcthefirst/SemanticModelDataMapper
Project-URL: Documentation, https://github.com/rxcthefirst/SemanticModelDataMapper#readme
Project-URL: Repository, https://github.com/rxcthefirst/SemanticModelDataMapper
Project-URL: Issues, https://github.com/rxcthefirst/SemanticModelDataMapper/issues
Project-URL: Changelog, https://github.com/rxcthefirst/SemanticModelDataMapper/blob/main/CHANGELOG.md
Keywords: rdf,ontology,semantic-web,knowledge-graph,owl,shacl,linked-data,data-conversion,skos,owl2,ttl,json-ld,csv-to-rdf,excel-to-rdf,json-to-rdf,xml-to-rdf,semantic-mapping,ontology-alignment,data-integration
Classifier: Development Status :: 4 - Beta
Classifier: Intended Audience :: Developers
Classifier: Intended Audience :: Science/Research
Classifier: Topic :: Scientific/Engineering :: Information Analysis
Classifier: Topic :: Software Development :: Libraries :: Python Modules
Classifier: Programming Language :: Python :: 3
Classifier: Programming Language :: Python :: 3.11
Classifier: Programming Language :: Python :: 3.12
Classifier: Programming Language :: Python :: 3.13
Requires-Python: >=3.11
License-File: LICENSE
Requires-Dist: rdflib>=7.0.0
Requires-Dist: polars>=0.19.0
Requires-Dist: openpyxl>=3.1.0
Requires-Dist: pydantic>=2.5.0
Requires-Dist: pydantic-settings>=2.1.0
Requires-Dist: pyshacl>=0.25.0
Requires-Dist: typer>=0.9.0
Requires-Dist: PyYAML>=6.0.1
Requires-Dist: python-dateutil>=2.8.2
Requires-Dist: rich>=13.7.0
Requires-Dist: click>=8.1.7
Requires-Dist: sentence-transformers>=2.2.0
Requires-Dist: scikit-learn>=1.3.0
Provides-Extra: dev
Requires-Dist: pytest>=7.4.3; extra == "dev"
Requires-Dist: pytest-cov>=4.1.0; extra == "dev"
Requires-Dist: mypy>=1.7.1; extra == "dev"
Requires-Dist: black>=23.12.0; extra == "dev"
Requires-Dist: ruff>=0.1.8; extra == "dev"
Requires-Dist: types-PyYAML>=6.0.12; extra == "dev"
Requires-Dist: types-python-dateutil>=2.8.19; extra == "dev"
Requires-Dist: psutil>=5.9.0; extra == "dev"
Dynamic: author
Dynamic: license-file
Dynamic: requires-python
